LICENSE
README.md
setup.cfg
setup.py
sshd_telegram_alert/__init__.py
sshd_telegram_alert/__main__.py
sshd_telegram_alert/configurations.py
sshd_telegram_alert/credentials.py
sshd_telegram_alert/parser.py
sshd_telegram_alert/requester.py
sshd_telegram_alert.egg-info/PKG-INFO
sshd_telegram_alert.egg-info/SOURCES.txt
sshd_telegram_alert.egg-info/dependency_links.txt
sshd_telegram_alert.egg-info/entry_points.txt
sshd_telegram_alert.egg-info/requires.txt
sshd_telegram_alert.egg-info/top_level.txt